diwrappers/__init__.py
diwrappers/_async_contextual_dependency.py
diwrappers/_async_dependency.py
diwrappers/_commons/__init__.py
diwrappers/_commons/_data.py
diwrappers/_commons/_exceptions.py
diwrappers/_contextual_dependency.py
diwrappers/_dependency.py
diwrappers/py.typed
diwrappers-0.5.0.dist-info/METADATA
diwrappers-0.5.0.dist-info/WHEEL
diwrappers-0.5.0.dist-info/RECORD
