Metadata-Version: 2.3
Name: diwrappers
Version: 0.5.0
Summary: A lightweight, intuitive dependency injection library for Python that makes testing and dependency management a breeze.
License: MIT
Author: Rui Campos
Author-email: mail@ruicampos.org
Requires-Python: >=3.10
Classifier: License :: OSI Approved :: MIT License
Classifier: Programming Language :: Python :: 3
Classifier: Programming Language :: Python :: 3.10
Classifier: Programming Language :: Python :: 3.11
Classifier: Programming Language :: Python :: 3.12
Classifier: Programming Language :: Python :: 3.13
Project-URL: Repository, https://github.com/ruifilipecampos/diwrappers
